setup.py
xesking/__init__.py
xesking.egg-info/PKG-INFO
xesking.egg-info/SOURCES.txt
xesking.egg-info/dependency_links.txt
xesking.egg-info/top_level.txt