Metadata-Version: 1.1
Name: xesking
Version: 0.0.1
Summary: 这个是C站的封装库，现在已上传到PyPi
Home-page: https://github.com/
Author: Yanming Guo
Author-email: gyms1111@163.com
License: UNKNOWN
Platform: UNKNOWN
Classifier: Programming Language :: Python :: 3
Classifier: License :: OSI Approved :: MIT License
Classifier: Operating System :: OS Independent
